jvsfunc/__init__.py
jvsfunc/blur.py
jvsfunc/deblend.py
jvsfunc/deinterlace.py
jvsfunc/denoise.py
jvsfunc/dotcrawl.py
jvsfunc/find.py
jvsfunc/helper.py
jvsfunc/mask.py
jvsfunc/misc.py
jvsfunc/py.typed
jvsfunc/util.py
jvsfunc-1.0.16.dist-info/LICENSE
jvsfunc-1.0.16.dist-info/METADATA
jvsfunc-1.0.16.dist-info/WHEEL
jvsfunc-1.0.16.dist-info/top_level.txt
jvsfunc-1.0.16.dist-info/RECORD
