Metadata-Version: 2.1
Name: jvsfunc
Version: 1.0.16
Summary: Julek VapourSynth functions
Home-page: https://github.com/dnjulek/jvsfunc
Author: Julek
License: MIT
Requires-Python: >=3.8
License-File: LICENSE
Requires-Dist: vapoursynth (>=58)
Requires-Dist: vsrgtools (>=0.1.4)
Requires-Dist: vsutil (>=0.8.0)
